{
  "info": {
    "_postman_id": "learnership-api-collection",
    "name": "Learnership API - Complete Test Collection",
    "description": "Comprehensive API testing collection for Learnership Management System",
    "schema": "https://schema.getpostman.com/json/collection/v2.1.0/collection.json"
  },
  "item": [
    {
      "name": "Authentication",
      "item": [
        {
          "name": "Login",
          "request": {
            "method": "POST",
            "header": [
              {
                "key": "Content-Type",
                "value": "application/json"
              }
            ],
            "body": {
              "mode": "raw",
              "raw": "{\n  \"email\": \"admin@example.com\",\n  \"password\": \"AdminPassword123\"\n}"
            },
            "url": {
              "raw": "{{base_url}}/api/auth/login",
              "host": ["{{base_url}}"],
              "path": ["api", "auth", "login"]
            }
          },
          "response": []
        },
        {
          "name": "Register",
          "request": {
            "method": "POST",
            "header": [
              {
                "key": "Content-Type",
                "value": "application/json"
              }
            ],
            "body": {
              "mode": "raw",
              "raw": "{\n  \"email\": \"newuser@example.com\",\n  \"password\": \"SecurePassword123\",\n  \"firstName\": \"John\",\n  \"lastName\": \"Doe\"\n}"
            },
            "url": {
              "raw": "{{base_url}}/api/auth/register",
              "host": ["{{base_url}}"],
              "path": ["api", "auth", "register"]
            }
          },
          "response": []
        },
        {
          "name": "Change Password",
          "request": {
            "method": "POST",
            "header": [
              {
                "key": "Content-Type",
                "value": "application/json"
              },
              {
                "key": "Authorization",
                "value": "Bearer {{token}}"
              }
            ],
            "body": {
              "mode": "raw",
              "raw": "{\n  \"oldPassword\": \"AdminPassword123\",\n  \"newPassword\": \"NewPassword123\",\n  \"confirmPassword\": \"NewPassword123\"\n}"
            },
            "url": {
              "raw": "{{base_url}}/api/auth/change-password",
              "host": ["{{base_url}}"],
              "path": ["api", "auth", "change-password"]
            }
          },
          "response": []
        }
      ]
    },
    {
      "name": "Students",
      "item": [
        {
          "name": "List Students - Default",
          "request": {
            "method": "GET",
            "header": [
              {
                "key": "Authorization",
                "value": "Bearer {{token}}"
              }
            ],
            "url": {
              "raw": "{{base_url}}/api/students",
              "host": ["{{base_url}}"],
              "path": ["api", "students"]
            }
          },
          "response": []
        },
        {
          "name": "List Students - Paginated",
          "request": {
            "method": "GET",
            "header": [
              {
                "key": "Authorization",
                "value": "Bearer {{token}}"
              }
            ],
            "url": {
              "raw": "{{base_url}}/api/students?page=1&pageSize=20",
              "host": ["{{base_url}}"],
              "path": ["api", "students"],
              "query": [
                {
                  "key": "page",
                  "value": "1"
                },
                {
                  "key": "pageSize",
                  "value": "20"
                }
              ]
            }
          },
          "response": []
        },
        {
          "name": "List Students - Filtered",
          "request": {
            "method": "GET",
            "header": [
              {
                "key": "Authorization",
                "value": "Bearer {{token}}"
              }
            ],
            "url": {
              "raw": "{{base_url}}/api/students?status=ACTIVE&groupId=550e8400-e29b-41d4-a716-446655440001",
              "host": ["{{base_url}}"],
              "path": ["api", "students"],
              "query": [
                {
                  "key": "status",
                  "value": "ACTIVE"
                },
                {
                  "key": "groupId",
                  "value": "550e8400-e29b-41d4-a716-446655440001"
                }
              ]
            }
          },
          "response": []
        },
        {
          "name": "Get Student",
          "request": {
            "method": "GET",
            "header": [
              {
                "key": "Authorization",
                "value": "Bearer {{token}}"
              }
            ],
            "url": {
              "raw": "{{base_url}}/api/students/550e8400-e29b-41d4-a716-446655440010",
              "host": ["{{base_url}}"],
              "path": ["api", "students", "550e8400-e29b-41d4-a716-446655440010"]
            }
          },
          "response": []
        },
        {
          "name": "Create Student",
          "request": {
            "method": "POST",
            "header": [
              {
                "key": "Authorization",
                "value": "Bearer {{token}}"
              },
              {
                "key": "Content-Type",
                "value": "application/json"
              }
            ],
            "body": {
              "mode": "raw",
              "raw": "{\n  \"firstName\": \"John\",\n  \"lastName\": \"Doe\",\n  \"email\": \"john.doe@example.com\",\n  \"phone\": \"+27721234567\",\n  \"studentId\": \"STU001\",\n  \"groupId\": \"550e8400-e29b-41d4-a716-446655440001\"\n}"
            },
            "url": {
              "raw": "{{base_url}}/api/students",
              "host": ["{{base_url}}"],
              "path": ["api", "students"]
            }
          },
          "response": []
        },
        {
          "name": "Update Student",
          "request": {
            "method": "PUT",
            "header": [
              {
                "key": "Authorization",
                "value": "Bearer {{token}}"
              },
              {
                "key": "Content-Type",
                "value": "application/json"
              }
            ],
            "body": {
              "mode": "raw",
              "raw": "{\n  \"firstName\": \"Updated\",\n  \"status\": \"ACTIVE\"\n}"
            },
            "url": {
              "raw": "{{base_url}}/api/students/550e8400-e29b-41d4-a716-446655440010",
              "host": ["{{base_url}}"],
              "path": ["api", "students", "550e8400-e29b-41d4-a716-446655440010"]
            }
          },
          "response": []
        }
      ]
    },
    {
      "name": "Groups",
      "item": [
        {
          "name": "List Groups",
          "request": {
            "method": "GET",
            "header": [
              {
                "key": "Authorization",
                "value": "Bearer {{token}}"
              }
            ],
            "url": {
              "raw": "{{base_url}}/api/groups",
              "host": ["{{base_url}}"],
              "path": ["api", "groups"]
            }
          },
          "response": []
        },
        {
          "name": "Get Group",
          "request": {
            "method": "GET",
            "header": [
              {
                "key": "Authorization",
                "value": "Bearer {{token}}"
              }
            ],
            "url": {
              "raw": "{{base_url}}/api/groups/550e8400-e29b-41d4-a716-446655440001",
              "host": ["{{base_url}}"],
              "path": ["api", "groups", "550e8400-e29b-41d4-a716-446655440001"]
            }
          },
          "response": []
        },
        {
          "name": "Create Group",
          "request": {
            "method": "POST",
            "header": [
              {
                "key": "Authorization",
                "value": "Bearer {{token}}"
              },
              {
                "key": "Content-Type",
                "value": "application/json"
              }
            ],
            "body": {
              "mode": "raw",
              "raw": "{\n  \"name\": \"Grade 10A\",\n  \"description\": \"Grade 10 Mathematics Group\",\n  \"code\": \"G10A2026\",\n  \"startDate\": \"2026-01-01T00:00:00Z\",\n  \"endDate\": \"2026-12-31T23:59:59Z\"\n}"
            },
            "url": {
              "raw": "{{base_url}}/api/groups",
              "host": ["{{base_url}}"],
              "path": ["api", "groups"]
            }
          },
          "response": []
        },
        {
          "name": "Update Group",
          "request": {
            "method": "PUT",
            "header": [
              {
                "key": "Authorization",
                "value": "Bearer {{token}}"
              },
              {
                "key": "Content-Type",
                "value": "application/json"
              }
            ],
            "body": {
              "mode": "raw",
              "raw": "{\n  \"name\": \"Grade 10A Updated\",\n  \"status\": \"ACTIVE\"\n}"
            },
            "url": {
              "raw": "{{base_url}}/api/groups/550e8400-e29b-41d4-a716-446655440001",
              "host": ["{{base_url}}"],
              "path": ["api", "groups", "550e8400-e29b-41d4-a716-446655440001"]
            }
          },
          "response": []
        }
      ]
    },
    {
      "name": "Assessments",
      "item": [
        {
          "name": "List Assessments",
          "request": {
            "method": "GET",
            "header": [
              {
                "key": "Authorization",
                "value": "Bearer {{token}}"
              }
            ],
            "url": {
              "raw": "{{base_url}}/api/assessments?page=1&pageSize=20",
              "host": ["{{base_url}}"],
              "path": ["api", "assessments"],
              "query": [
                {
                  "key": "page",
                  "value": "1"
                },
                {
                  "key": "pageSize",
                  "value": "20"
                }
              ]
            }
          },
          "response": []
        },
        {
          "name": "Get Assessment",
          "request": {
            "method": "GET",
            "header": [
              {
                "key": "Authorization",
                "value": "Bearer {{token}}"
              }
            ],
            "url": {
              "raw": "{{base_url}}/api/assessments/550e8400-e29b-41d4-a716-446655440020",
              "host": ["{{base_url}}"],
              "path": ["api", "assessments", "550e8400-e29b-41d4-a716-446655440020"]
            }
          },
          "response": []
        },
        {
          "name": "Create Assessment",
          "request": {
            "method": "POST",
            "header": [
              {
                "key": "Authorization",
                "value": "Bearer {{token}}"
              },
              {
                "key": "Content-Type",
                "value": "application/json"
              }
            ],
            "body": {
              "mode": "raw",
              "raw": "{\n  \"name\": \"Mid-Year Exam\",\n  \"description\": \"Mathematics mid-year assessment\",\n  \"status\": \"DRAFT\",\n  \"groupId\": \"550e8400-e29b-41d4-a716-446655440001\",\n  \"totalMarks\": 100,\n  \"dueDate\": \"2026-06-30T00:00:00Z\"\n}"
            },
            "url": {
              "raw": "{{base_url}}/api/assessments",
              "host": ["{{base_url}}"],
              "path": ["api", "assessments"]
            }
          },
          "response": []
        }
      ]
    },
    {
      "name": "Attendance",
      "item": [
        {
          "name": "Mark Attendance - Single",
          "request": {
            "method": "POST",
            "header": [
              {
                "key": "Authorization",
                "value": "Bearer {{token}}"
              },
              {
                "key": "Content-Type",
                "value": "application/json"
              }
            ],
            "body": {
              "mode": "raw",
              "raw": "{\n  \"studentId\": \"550e8400-e29b-41d4-a716-446655440010\",\n  \"sessionId\": \"550e8400-e29b-41d4-a716-446655440020\",\n  \"status\": \"PRESENT\"\n}"
            },
            "url": {
              "raw": "{{base_url}}/api/attendance",
              "host": ["{{base_url}}"],
              "path": ["api", "attendance"]
            }
          },
          "response": []
        },
        {
          "name": "Mark Attendance - Bulk",
          "request": {
            "method": "POST",
            "header": [
              {
                "key": "Authorization",
                "value": "Bearer {{token}}"
              },
              {
                "key": "Content-Type",
                "value": "application/json"
              }
            ],
            "body": {
              "mode": "raw",
              "raw": "{\n  \"records\": [\n    {\n      \"studentId\": \"550e8400-e29b-41d4-a716-446655440010\",\n      \"sessionId\": \"550e8400-e29b-41d4-a716-446655440020\",\n      \"status\": \"PRESENT\"\n    },\n    {\n      \"studentId\": \"550e8400-e29b-41d4-a716-446655440011\",\n      \"sessionId\": \"550e8400-e29b-41d4-a716-446655440020\",\n      \"status\": \"ABSENT\"\n    },\n    {\n      \"studentId\": \"550e8400-e29b-41d4-a716-446655440012\",\n      \"sessionId\": \"550e8400-e29b-41d4-a716-446655440020\",\n      \"status\": \"LATE\"\n    }\n  ]\n}"
            },
            "url": {
              "raw": "{{base_url}}/api/attendance/bulk",
              "host": ["{{base_url}}"],
              "path": ["api", "attendance", "bulk"]
            }
          },
          "response": []
        }
      ]
    },
    {
      "name": "Error Cases - Testing",
      "item": [
        {
          "name": "Invalid Email Format",
          "request": {
            "method": "POST",
            "header": [
              {
                "key": "Authorization",
                "value": "Bearer {{token}}"
              },
              {
                "key": "Content-Type",
                "value": "application/json"
              }
            ],
            "body": {
              "mode": "raw",
              "raw": "{\n  \"firstName\": \"Test\",\n  \"lastName\": \"User\",\n  \"email\": \"invalid-email\",\n  \"groupId\": \"550e8400-e29b-41d4-a716-446655440001\"\n}"
            },
            "url": {
              "raw": "{{base_url}}/api/students",
              "host": ["{{base_url}}"],
              "path": ["api", "students"]
            }
          },
          "response": []
        },
        {
          "name": "Missing Required Fields",
          "request": {
            "method": "POST",
            "header": [
              {
                "key": "Authorization",
                "value": "Bearer {{token}}"
              },
              {
                "key": "Content-Type",
                "value": "application/json"
              }
            ],
            "body": {
              "mode": "raw",
              "raw": "{\n  \"firstName\": \"Test\"\n}"
            },
            "url": {
              "raw": "{{base_url}}/api/students",
              "host": ["{{base_url}}"],
              "path": ["api", "students"]
            }
          },
          "response": []
        },
        {
          "name": "Invalid UUID",
          "request": {
            "method": "GET",
            "header": [
              {
                "key": "Authorization",
                "value": "Bearer {{token}}"
              }
            ],
            "url": {
              "raw": "{{base_url}}/api/students/not-a-uuid",
              "host": ["{{base_url}}"],
              "path": ["api", "students", "not-a-uuid"]
            }
          },
          "response": []
        },
        {
          "name": "Non-Existent Resource",
          "request": {
            "method": "GET",
            "header": [
              {
                "key": "Authorization",
                "value": "Bearer {{token}}"
              }
            ],
            "url": {
              "raw": "{{base_url}}/api/students/00000000-0000-0000-0000-000000000000",
              "host": ["{{base_url}}"],
              "path": ["api", "students", "00000000-0000-0000-0000-000000000000"]
            }
          },
          "response": []
        },
        {
          "name": "Bulk Attendance - Exceeds Limit",
          "request": {
            "method": "POST",
            "header": [
              {
                "key": "Authorization",
                "value": "Bearer {{token}}"
              },
              {
                "key": "Content-Type",
                "value": "application/json"
              }
            ],
            "body": {
              "mode": "raw",
              "raw": "{\n  \"records\": []\n}"
            },
            "url": {
              "raw": "{{base_url}}/api/attendance/bulk",
              "host": ["{{base_url}}"],
              "path": ["api", "attendance", "bulk"]
            }
          },
          "response": []
        },
        {
          "name": "Missing Authentication",
          "request": {
            "method": "GET",
            "header": [],
            "url": {
              "raw": "{{base_url}}/api/students",
              "host": ["{{base_url}}"],
              "path": ["api", "students"]
            }
          },
          "response": []
        }
      ]
    }
  ],
  "variable": [
    {
      "key": "base_url",
      "value": "http://localhost:3000",
      "type": "string"
    },
    {
      "key": "token",
      "value": "",
      "type": "string"
    }
  ]
}
